pyronn/__init__.py
pyronn/ct_reconstruction/__init__.py
pyronn/ct_reconstruction/geometry/__init__.py
pyronn/ct_reconstruction/geometry/geometry_base.py
pyronn/ct_reconstruction/geometry/geometry_cone_3d.py
pyronn/ct_reconstruction/geometry/geometry_fan_2d.py
pyronn/ct_reconstruction/geometry/geometry_parallel_2d.py
pyronn/ct_reconstruction/geometry/geometry_parallel_3d.py
pyronn/ct_reconstruction/helpers/__init__.py
pyronn/ct_reconstruction/helpers/filters/__init__.py
pyronn/ct_reconstruction/helpers/filters/filters.py
pyronn/ct_reconstruction/helpers/filters/weights.py
pyronn/ct_reconstruction/helpers/misc/__init__.py
pyronn/ct_reconstruction/helpers/misc/generate_reco.py
pyronn/ct_reconstruction/helpers/misc/generate_sinogram.py
pyronn/ct_reconstruction/helpers/phantoms/__init__.py
pyronn/ct_reconstruction/helpers/phantoms/primitives_2d.py
pyronn/ct_reconstruction/helpers/phantoms/primitives_3d.py
pyronn/ct_reconstruction/helpers/phantoms/shepp_logan.py
pyronn/ct_reconstruction/helpers/trajectories/__init__.py
pyronn/ct_reconstruction/helpers/trajectories/circular_trajectory.py
pyronn/ct_reconstruction/layers/__init__.py
pyronn/ct_reconstruction/layers/backprojection_2d.py
pyronn/ct_reconstruction/layers/backprojection_3d.py
pyronn/ct_reconstruction/layers/projection_2d.py
pyronn/ct_reconstruction/layers/projection_3d.py
pyronn-0.1.0.dist-info/LICENSE
pyronn-0.1.0.dist-info/METADATA
pyronn-0.1.0.dist-info/WHEEL
pyronn-0.1.0.dist-info/top_level.txt
pyronn-0.1.0.dist-info/RECORD
