Metadata-Version: 2.1
Name: pyronn
Version: 0.1.0
Summary: PYRO-NN is the high level Python API to the PYRO-NN-Layers known operators.
Home-page: https://github.com/csyben/PYRO-NN
Author: Christopher Syben
Author-email: christopher.syben@fau.de
License: UNKNOWN
Platform: UNKNOWN
Classifier: Programming Language :: Python :: 3
Classifier: License :: OSI Approved :: Apache Software License
Classifier: Operating System :: OS Independent
Requires-Dist: numpy
Requires-Dist: pyronn-layers (>=0.1.0)
